LICENSE.txt
README.md
setup.cfg
setup.py
image2str/__init__.py
image2str/image2str.py
image2str.egg-info/PKG-INFO
image2str.egg-info/SOURCES.txt
image2str.egg-info/dependency_links.txt
image2str.egg-info/requires.txt
image2str.egg-info/top_level.txt