Metadata-Version: 2.1
Name: image2str
Version: 1.0.2
Summary: Transform image to ansi string
Download-URL: https://github.com/user/reponame/archive/v_01.tar.gz
License: MIT
Keywords: img,image,terminal,show image on terminal,ansi,ANSI
Classifier: Development Status :: 5 - Production/Stable
Classifier: Intended Audience :: Developers
Classifier: License :: OSI Approved :: MIT License
Classifier: Programming Language :: Python :: 3
Classifier: Programming Language :: Python :: 3.9
Classifier: Programming Language :: Python :: 3.10
Classifier: Programming Language :: Python :: 3.11
License-File: LICENSE.txt
